DataStr/__init__.py
DataStr-1.2.0.dist-info/LICENSE
DataStr-1.2.0.dist-info/METADATA
DataStr-1.2.0.dist-info/WHEEL
DataStr-1.2.0.dist-info/top_level.txt
DataStr-1.2.0.dist-info/RECORD
