Metadata-Version: 2.1
Name: DataStr
Version: 1.2.0
Summary: DataStr is a module that allows easy implementation of stack and queue operations with minimal code.
Home-page: https://github.com/Prithwis-2023/DataStr
Author: Prithwis
Author-email: prithwisdas2017@gmail.com
Project-URL: Bug Tracker, https://github.com/pypa/sampleproject/issues
Classifier: Programming Language :: Python :: 3
Classifier: License :: OSI Approved :: MIT License
Classifier: Operating System :: OS Independent
Requires-Python: >=3.7
License-File: LICENSE
